ljtool/__init__.py
ljtool/converter.py
ljtool/lj_amazon/__init__.py
ljtool/lj_amazon/data_from.py
ljtool/lj_amazon/url_parse.py
ljtool/lj_db/__init__.py
ljtool/lj_headers/__init__.py
ljtool/lj_headers/headers_format.py
ljtool/lj_p/__init__.py
ljtool/lj_p/singleton.py
ljtool-0.0.3.dist-info/LICENSE
ljtool-0.0.3.dist-info/METADATA
ljtool-0.0.3.dist-info/WHEEL
ljtool-0.0.3.dist-info/entry_points.txt
ljtool-0.0.3.dist-info/top_level.txt
ljtool-0.0.3.dist-info/RECORD
